pdfshrink/__init__.py
pdfshrink-0.1.0.dist-info/LICENSE
pdfshrink-0.1.0.dist-info/METADATA
pdfshrink-0.1.0.dist-info/WHEEL
pdfshrink-0.1.0.dist-info/entry_points.txt
pdfshrink-0.1.0.dist-info/top_level.txt
pdfshrink-0.1.0.dist-info/RECORD
