Metadata-Version: 2.1
Name: pdfshrink
Version: 0.1.0
Summary: Script of shrink PDF files (wrapper around GhostScript)
Home-page: https://github.com/tdegeus/pdfshrink
Author: Tom de Geus
Author-email: tom@geus.me
License: MIT
Keywords: PDF,GhostScript
Platform: UNKNOWN
Requires-Dist: docopt (>=0.6.2)
Requires-Dist: click (>=4.0)
